understory/cache/__init__.py
understory/cache/templates/__init__.py
understory/cache/templates/domain.html
understory/cache/templates/index.html
understory/cache/templates/resource.html
understory_cache-0.0.2.dist-info/LICENSE
understory_cache-0.0.2.dist-info/WHEEL
understory_cache-0.0.2.dist-info/METADATA
understory_cache-0.0.2.dist-info/RECORD
