Metadata-Version: 2.1
Name: understory-cache
Version: 0.0.2
Summary: Cache URLs and their contents
License: AGPL-3.0-or-later
Author: Angelo Gladding
Author-email: angelo@ragt.ag
Requires-Python: >=3.9,<4.0
Classifier: License :: OSI Approved :: GNU Affero General Public License v3 or later (AGPLv3+)
Classifier: Programming Language :: Python :: 3
Classifier: Programming Language :: Python :: 3.9
